{
  "spreadshot_gun_pickup": {
    "components": {
      "Position": {},
      "Velocity": { "dx": -50 },
      "Sprite": { 
        "texture_path": "Assets/sprites/powerup_spreadshot.png",
        "frame_width": 100, 
        "frame_height": 85, 
        "z_index": 20, 
        "rect_x": 25, 
        "rect_y": 150 
      },
      "Scale": { "width": 0.2, "height": 0.2 },
      "Hitbox": { "width": 28, "height": 28 },
      "PowerUp": { 
        "type": "CHANGE_WEAPON", 
        "data": { "weapon_archetype": "weapons.spread_gun" }
      }
    }
  },
  "laser_gun_pickup": {
    "components": {
      "Position": {},
      "Velocity": { "dx": -50 },
      "Sprite": { 
        "texture_path": "Assets/sprites/powerup_change_weapon.png", 
        "frame_width": 115,
        "frame_height": 75,
        "z_index": 20, 
        "rect_x": 10, 
        "rect_y": 225 
      },
      "Animation": { "start_frame": 0, "num_frames": 3, "duration": 0.1, "loops": true },
      "Scale": { "width": 0.2, "height": 0.2 },
      "Hitbox": { "width": 28, "height": 14 },
      "PowerUp": { 
        "type": "CHANGE_WEAPON",
        "data": {
          "weapon_archetype": "weapons.laser_gun"
        }
      }
    }
  },
  "spread_gun_pickup": {
    "components": {
      "Position": {},
      "Velocity": { "dx": -50 },
      "Sprite": { 
        "texture_path": "Assets/sprites/powerup_change_weapon.png", 
        "frame_width": 115,
        "frame_height": 75,
        "z_index": 20, 
        "rect_x": 10, 
        "rect_y": 225 
      },
      "Animation": { "start_frame": 0, "num_frames": 3, "duration": 0.1, "loops": true },
      "Scale": { "width": 0.2, "height": 0.2 },
      "Hitbox": { "width": 28, "height": 14 },
      "PowerUp": { 
        "type": "CHANGE_WEAPON",
        "data": {
          "weapon_archetype": "weapons.spread_gun"
        }
      }
    }
  },
  "simple_gun_pickup": {
    "components": {
      "Position": {},
      "Velocity": { "dx": -50 },
      "Sprite": { 
        "texture_path": "Assets/sprites/powerup_change_weapon.png", 
        "frame_width": 115,
        "frame_height": 75,
        "z_index": 20, 
        "rect_x": 10, 
        "rect_y": 225 
      },
      "Animation": { "start_frame": 0, "num_frames": 3, "duration": 0.1, "loops": true },
      "Scale": { "width": 0.2, "height": 0.2 },
      "Hitbox": { "width": 28, "height": 14 },
      "PowerUp": { 
        "type": "CHANGE_WEAPON",
        "data": {
          "weapon_archetype": "weapons.simple_gun"
        }
      }
    }
  },
  "heal_pickup_small": {
    "components": {
      "Position": {},
      "Velocity": { "dx": -50 },
      "Sprite": { 
        "texture_path": "Assets/sprites/powerup_health_small.png", 
        "frame_width": 133, 
        "frame_height": 250, 
        "z_index": 20, 
        "rect_x": 0, 
        "rect_y": 75 
      },
      "Animation": { "start_frame": 0, "num_frames": 5, "duration": 0.1, "loops": true },
      "Scale": { "width": 0.2, "height": 0.2 },
      "Hitbox": { "width": 20, "height": 20 },
      "PowerUp": {
        "type": "HEAL",
        "data": { "amount": 25 }
      }
    }
  },
  "heal_pickup_large": {
    "components": {
      "Position": {},
      "Velocity": { "dx": -50 },
      "Sprite": { 
        "texture_path": "Assets/sprites/powerup_health_large.png", 
        "frame_width": 99, 
        "frame_height": 300, 
        "z_index": 20, 
        "rect_x": 5, 
        "rect_y": 100 
      },
      "Animation": { "start_frame": 0, "num_frames": 5, "duration": 0.1, "loops": true },
      "Scale": { "width": 0.2, "height": 0.2 },
      "Hitbox": { "width": 20, "height": 20 },
      "PowerUp": {
        "type": "HEAL",
        "data": { "amount": 25 }
      }
    }
  },
  "score_pickup_bronze": {
    "components": {
      "Position": {},
      "Velocity": { "dx": -50 },
      "Sprite": { 
        "texture_path": "Assets/sprites/powerup_score_bronze.png", 
        "frame_width": 81, 
        "frame_height": 100, 
        "z_index": 20, 
        "rect_x": 7, 
        "rect_y": 150
      },
      "Animation": { "start_frame": 0, "num_frames": 6, "duration": 0.1, "loops": true },
      "Scale": { "width": 0.2, "height": 0.2 },
      "Hitbox": { "width": 14, "height": 14 },
      "PowerUp": {
        "type": "ADD_SCORE",
        "data": { "value": 500 }
      }
    }
  },
  "score_pickup_silver": {
    "components": {
      "Position": {},
      "Velocity": { "dx": -50 },
      "Sprite": { 
        "texture_path": "Assets/sprites/powerup_score_silver.png", 
        "frame_width": 81, 
        "frame_height": 100, 
        "z_index": 20, 
        "rect_x": 6, 
        "rect_y": 180
      },
      "Animation": { "start_frame": 0, "num_frames": 6, "duration": 0.1, "loops": true },
      "Scale": { "width": 0.2, "height": 0.2 },
      "Hitbox": { "width": 18, "height": 18 },
      "PowerUp": {
        "type": "ADD_SCORE",
        "data": { "value": 1000 }
      }
    }
  },
  "score_pickup_gold": {
    "components": {
      "Position": {},
      "Velocity": { "dx": -50 },
      "Sprite": { 
        "texture_path": "Assets/sprites/powerup_score_gold.png", 
        "frame_width": 81, 
        "frame_height": 100, 
        "z_index": 20, 
        "rect_x": 6, 
        "rect_y": 150
      },
      "Animation": { "start_frame": 0, "num_frames": 6, "duration": 0.1, "loops": true },
      "Scale": { "width": 0.2, "height": 0.2 },
      "Hitbox": { "width": 22, "height": 22 },
      "PowerUp": {
        "type": "ADD_SCORE",
        "data": { "value": 2500 }
      }
    }
  },
  "shield_pickup": {
    "components": {
      "Position": {},
      "Velocity": { "dx": -50 },
      "Sprite": { 
        "texture_path": "Assets/sprites/powerup_shield.png", 
        "frame_width": 120, 
        "frame_height": 100, 
        "z_index": 20, 
        "rect_x": 6, 
        "rect_y": 150
      },
      "Animation": { "start_frame": 0, "num_frames": 4, "duration": 0.1, "loops": true },
      "Scale": { "width": 0.2, "height": 0.2 },
      "Hitbox": { "width": 24, "height": 24 },
      "PowerUp": {
        "type": "SHIELD",
        "data": { "amount": 100 }
      }
    }
  },
  "speed_boost_pickup": {
    "components": {
      "Position": {},
      "Velocity": { "dx": -50 },
      "Sprite": { 
        "texture_path": "Assets/sprites/powerup_speed.png", 
        "frame_width": 120, 
        "frame_height": 100, 
        "z_index": 20, 
        "rect_x": 6, 
        "rect_y": 200
      },
      "Animation": { "start_frame": 0, "num_frames": 4, "duration": 0.1, "loops": true },
      "Scale": { "width": 0.2, "height": 0.2 },
      "Hitbox": { "width": 18, "height": 18 },
      "PowerUp": {
        "type": "SPEED_BOOST",
        "data": { "multiplier": 1.5, "duration": 5.0 }
      }
    }
  }
}
